Metadata-Version: 2.1
Name: GitLab.py
Version: 0.111
Summary: My CMD 模組
Home-page: UNKNOWN
License: LGPL
Platform: UNKNOWN
